pyktionary/__init__.py
pyktionary/models.py
pyktionary-0.7.1.dist-info/LICENCE
pyktionary-0.7.1.dist-info/METADATA
pyktionary-0.7.1.dist-info/WHEEL
pyktionary-0.7.1.dist-info/top_level.txt
pyktionary-0.7.1.dist-info/RECORD
