Metadata-Version: 2.1
Name: pyktionary
Version: 0.7.1
Summary: Simple Wiktionary scraper
Home-page: https://gitlab.com/flow.gunso/pyktionary
Author: flow.gunso
Author-email: flow.gunso@gmail.com
License: UNKNOWN
Platform: UNKNOWN
Classifier: Development Status :: 5 - Production/Stable
Classifier: Intended Audience :: Developers
Classifier: License :: OSI Approved :: GNU General Public License v3 (GPLv3)
Classifier: Operating System :: OS Independent
Classifier: Programming Language :: Python
Classifier: Topic :: Internet :: WWW/HTTP :: Dynamic Content :: Wiki
Classifier: Topic :: Software Development :: Libraries :: Python Modules
Classifier: Topic :: Text Processing
Classifier: Topic :: Utilities
Requires-Dist: beautifulsoup4 (==4.6.3)
Requires-Dist: requests (==2.20.1)
